zqykj_modelcalc_client/__init__.py
zqykj_modelcalc_client/tools.py
zqykj_modelcalc_client/web.py
zqykj_modelcalc_client-1.0.3.dist-info/METADATA
zqykj_modelcalc_client-1.0.3.dist-info/WHEEL
zqykj_modelcalc_client-1.0.3.dist-info/top_level.txt
zqykj_modelcalc_client-1.0.3.dist-info/RECORD
